LICENSE.txt
MANIFEST.in
README.md
pyproject.toml
setup.cfg
setup.py
DiskAnalyzer/DiskAnalyzer.py
DiskAnalyzer/ExFatBootSector.py
DiskAnalyzer/MbrRepair.py
DiskAnalyzer/MftAnalyzer.py
DiskAnalyzer/NtfsAnalyzer.py
DiskAnalyzer/__init__.py
DiskAnalyzer/__main__.py
DiskAnalyzer.egg-info/PKG-INFO
DiskAnalyzer.egg-info/SOURCES.txt
DiskAnalyzer.egg-info/dependency_links.txt
DiskAnalyzer.egg-info/entry_points.txt
DiskAnalyzer.egg-info/top_level.txt