Metadata-Version: 2.2
Name: DiskAnalyzer
Version: 0.1.0
Summary: This package implements multiples libraries and tools to parse, analyze and extract informations from disk on the live system.
Home-page: https://github.com/mauricelambert/DiskAnalyzer
Download-URL: https://mauricelambert.github.io/info/python/security/DiskAnalyzer.pyz
Author: Maurice Lambert
Author-email: Maurice Lambert <mauricelambert434@gmail.com>
Maintainer: Maurice Lambert
Maintainer-email: Maurice Lambert <mauricelambert434@gmail.com>
License: GPL-3.0 License
Project-URL: Github, https://github.com/mauricelambert/DiskAnalyzer
Project-URL: Documentation, https://mauricelambert.github.io/info/python/security/DiskAnalyzer.html
Project-URL: Python Executable, https://mauricelambert.github.io/info/python/security/DiskAnalyzer.pyz
Project-URL: Windows Executable, https://mauricelambert.github.io/info/python/security/DiskAnalyzer.exe
Keywords: MFT,DiskAnalysis,Forensic,VBR,MBR,GPT,Windows,DFIR,IncidentResponse
Platform: Windows
Platform: Linux
Platform: MacOS
Classifier: Topic :: System
Classifier: Topic :: Security
Classifier: Environment :: Console
Classifier: Topic :: System :: Shells
Classifier: Operating System :: POSIX
Classifier: Natural Language :: English
Classifier: Programming Language :: Python
Classifier: Intended Audience :: Developers
Classifier: Topic :: System :: System Shells
Classifier: Operating System :: MacOS :: MacOS X
Classifier: Programming Language :: Python :: 3.8
Classifier: Operating System :: Microsoft :: Windows
Classifier: Topic :: System :: Systems Administration
Classifier: Intended Audience :: System Administrators
Classifier: Development Status :: 5 - Production/Stable
Classifier: License :: OSI Approved :: GNU General Public License v3 or later (GPLv3+)
Requires-Python: >=3.8
License-File: LICENSE.txt
Dynamic: author
Dynamic: download-url
Dynamic: home-page
Dynamic: maintainer
Dynamic: requires-python
